kavi_research_assistant_mcp/__init__.py
kavi_research_assistant_mcp/logo_data.py
kavi_research_assistant_mcp/server.py
kavi_research_assistant_mcp/ui.py
kavi_research_assistant_mcp-2.1.0.dist-info/METADATA
kavi_research_assistant_mcp-2.1.0.dist-info/WHEEL
kavi_research_assistant_mcp-2.1.0.dist-info/entry_points.txt
kavi_research_assistant_mcp-2.1.0.dist-info/licenses/LICENSE
kavi_research_assistant_mcp-2.1.0.dist-info/RECORD
