Metadata-Version: 2.4
Name: kavi-research-assistant-mcp
Version: 2.1.0
Summary: A Model Context Protocol server for research assistance with ChromaDB vector storage by kavi.ai
Project-URL: Homepage, https://github.com/machhakiran/kavi-research-assistant-mcp
Project-URL: Repository, https://github.com/machhakiran/kavi-research-assistant-mcp
Project-URL: Issues, https://github.com/machhakiran/kavi-research-assistant-mcp
Author-email: Machha Kiran <machhakiran@gmail.com>
License-File: LICENSE
Keywords: ai,chromadb,kavi.ai,langchain,mcp,research,vector-database
Classifier: Development Status :: 4 - Beta
Classifier: Intended Audience :: Developers
Classifier: License :: OSI Approved :: MIT License
Classifier: Programming Language :: Python :: 3
Classifier: Programming Language :: Python :: 3.11
Classifier: Programming Language :: Python :: 3.12
Requires-Python: >=3.11
Requires-Dist: chromadb>=1.1.0
Requires-Dist: docx2txt>=0.9
Requires-Dist: fastapi>=0.116.1
Requires-Dist: fastmcp>=2.12.3
Requires-Dist: gradio>=5.0.0
Requires-Dist: langchain-chroma>=0.2.6
Requires-Dist: langchain-community>=0.3.29
Requires-Dist: langchain-mcp-adapters>=0.1.9
Requires-Dist: langchain-ollama>=0.3.8
Requires-Dist: langchain-openai>=0.3.33
Requires-Dist: langchain-text-splitters>=1.1.0
Requires-Dist: langchain>=0.3.27
Requires-Dist: langgraph>=0.6.7
Requires-Dist: matplotlib>=3.10.6
Requires-Dist: mcp-use[search]>=1.3.10
Requires-Dist: mcp[cli]>=1.14.0
Requires-Dist: numpy>=2.3.3
Requires-Dist: openai>=1.108.1
Requires-Dist: pandas>=2.3.2
Requires-Dist: pypdf2>=3.0.1
Requires-Dist: pytest>=8.0.0
Requires-Dist: python-dotenv>=1.1.1
Requires-Dist: requests>=2.32.5
Requires-Dist: scipy>=1.16.2
